spiderx/__init__.py
spiderx/brower.py
spiderx/browserCookie3.py
spiderx/flask_server.py
spiderx/gui.py
spiderx/info.py
spiderx/my_pyqt.py
spiderx/my_sqlalchemy.py
spiderx/orm.py
spiderx/shiti.py
spiderx/sql.py
spiderx/sx.py
spiderx/tools.py
spiderx/tsparse.py
spiderx/utils.py
spiderx/win32.py
spiderx-1.12.44.dist-info/METADATA
spiderx-1.12.44.dist-info/WHEEL
spiderx-1.12.44.dist-info/top_level.txt
spiderx-1.12.44.dist-info/RECORD
